llm_auto_context/__init__.py
llm_auto_context/cli.py
llm_auto_context/config.py
llm_auto_context/snapshot.py
llm_auto_context-1.1.0.dist-info/METADATA
llm_auto_context-1.1.0.dist-info/WHEEL
llm_auto_context-1.1.0.dist-info/entry_points.txt
llm_auto_context-1.1.0.dist-info/top_level.txt
llm_auto_context-1.1.0.dist-info/RECORD
